viggocorev2/__init__.py
viggocorev2/_version.py
viggocorev2/celery.py
viggocorev2/database.py
viggocorev2/migration_utils.py
viggocorev2/queue.py
viggocorev2/request.py
viggocorev2/resources.py
viggocorev2/scheduler.py
viggocorev2/schema_manager.py
viggocorev2/system.py
viggocorev2/bootstrap/__init__.py
viggocorev2/bootstrap/roles.py
viggocorev2/bootstrap/routes.py
viggocorev2/bootstrap/default/__init__.py
viggocorev2/bootstrap/default/application.py
viggocorev2/bootstrap/default/domain.py
viggocorev2/bootstrap/default/policies.py
viggocorev2/bootstrap/default/user.py
viggocorev2/common/__init__.py
viggocorev2/common/controller.py
viggocorev2/common/exception.py
viggocorev2/common/input.py
viggocorev2/common/manager.py
viggocorev2/common/operation_after_post.py
viggocorev2/common/utils.py
viggocorev2/common/valida_cpf_cnpj.py
viggocorev2/common/subsystem/__init__.py
viggocorev2/common/subsystem/apihandler.py
viggocorev2/common/subsystem/controller.py
viggocorev2/common/subsystem/driver.py
viggocorev2/common/subsystem/entity.py
viggocorev2/common/subsystem/manager.py
viggocorev2/common/subsystem/operation.py
viggocorev2/common/subsystem/pagination.py
viggocorev2/common/subsystem/router.py
viggocorev2/common/subsystem/schema_model.py
viggocorev2/common/subsystem/transaction_manager.py
viggocorev2/common/subsystem/gerar_pdf/__init__.py
viggocorev2/common/subsystem/gerar_pdf/layout_padrao_html.py
viggocorev2/common/subsystem/gerar_pdf/relatorio_html.py
viggocorev2/common/subsystem/gerar_pdf/relatorio_utils.py
viggocorev2/common/subsystem/gerar_pdf/relatorio_styles/__init__.py
viggocorev2/common/subsystem/gerar_pdf/relatorio_styles/style_1.py
viggocorev2/common/subsystem/gerar_pdf/relatorio_styles/style_2.py
viggocorev2/common/subsystem/gerar_pdf/relatorio_styles/style_3.py
viggocorev2/common/subsystem/gerar_pdf/relatorio_styles/style_4.py
viggocorev2/common/subsystem/gerar_pdf/relatorio_styles/style_5.py
viggocorev2-1.0.3.dist-info/licenses/AUTHORS
viggocorev2-1.0.3.dist-info/licenses/LICENSE
viggocorev2-1.0.3.dist-info/METADATA
viggocorev2-1.0.3.dist-info/WHEEL
viggocorev2-1.0.3.dist-info/top_level.txt
viggocorev2-1.0.3.dist-info/RECORD
