Metadata-Version: 2.4
Name: viggocorev2
Version: 1.0.3
Summary: ViggocoreV2 Framework
Home-page: https://github.com/viggosistemas/viggocorev2-backend
Author: Jorge Júnio da Silva
Author-email: jorgejunioufrn@gmail.com
License: Apache-2.0
Requires-Python: >=3.8
License-File: LICENSE
License-File: AUTHORS
Requires-Dist: alembic==1.16.5
Requires-Dist: amqp==5.3.1
Requires-Dist: APScheduler==3.7.0
Requires-Dist: attrs==21.2.0
Requires-Dist: backports-datetime-fromisoformat==2.0.3
Requires-Dist: billiard==4.2.1
Requires-Dist: blinker==1.9.0
Requires-Dist: celery==5.3.4
Requires-Dist: certifi==2021.10.8
Requires-Dist: chardet==4.0.0
Requires-Dist: click==8.2.1
Requires-Dist: click-didyoumean==0.3.1
Requires-Dist: click-plugins==1.1.1
Requires-Dist: click-repl==0.3.0
Requires-Dist: colorama==0.4.4
Requires-Dist: decorator==5.0.8
Requires-Dist: et_xmlfile==2.0.0
Requires-Dist: Flask==3.0.1
Requires-Dist: Flask-JWT-Extended==4.6.0
Requires-Dist: Flask-Migrate==4.0.5
Requires-Dist: Flask-RBAC==0.5.0
Requires-Dist: Flask-SQLAlchemy==3.1.1
Requires-Dist: gabbi==2.2.0
Requires-Dist: greenlet==3.2.4
Requires-Dist: idna==2.10
Requires-Dist: iniconfig==1.1.1
Requires-Dist: itsdangerous==2.2.0
Requires-Dist: Jinja2==3.1.6
Requires-Dist: jsonpath-rw==1.4.0
Requires-Dist: jsonpath-rw-ext==1.2.2
Requires-Dist: kombu==5.3.7
Requires-Dist: Mako==1.3.10
Requires-Dist: MarkupSafe==3.0.2
Requires-Dist: marshmallow==4.0.0
Requires-Dist: marshmallow-sqlalchemy==0.30.0
Requires-Dist: openpyxl==3.0.7
Requires-Dist: packaging==25.0
Requires-Dist: pbr==5.6.0
Requires-Dist: pika==1.2.0
Requires-Dist: Pillow==9.1.0
Requires-Dist: pluggy==0.13.1
Requires-Dist: ply==3.11
Requires-Dist: prompt_toolkit==3.0.52
Requires-Dist: py==1.10.0
Requires-Dist: pyparsing==2.4.7
Requires-Dist: pytest==6.2.4
Requires-Dist: python-dateutil==2.9.0.post0
Requires-Dist: python-editor==1.0.4
Requires-Dist: pytz==2021.1
Requires-Dist: PyYAML==6.0
Requires-Dist: requests==2.25.1
Requires-Dist: six==1.16.0
Requires-Dist: sparkpost==1.3.9
Requires-Dist: SQLAlchemy==2.0.43
Requires-Dist: tomli==2.2.1
Requires-Dist: typing_extensions==4.15.0
Requires-Dist: tzdata==2025.2
Requires-Dist: tzlocal==2.1
Requires-Dist: urllib3==1.26.5
Requires-Dist: vine==5.0.0
Requires-Dist: wcwidth==0.2.5
Requires-Dist: Werkzeug==3.1.3
Requires-Dist: wsgi-intercept==1.9.2
Dynamic: author
Dynamic: author-email
Dynamic: description
Dynamic: description-content-type
Dynamic: home-page
Dynamic: license
Dynamic: license-file
Dynamic: requires-dist
Dynamic: requires-python
Dynamic: summary
